voluxaudio/__init__.py
voluxaudio/__version__.py
voluxaudio/computer.py
voluxaudio-0.9.0.dist-info/METADATA
voluxaudio-0.9.0.dist-info/WHEEL
voluxaudio-0.9.0.dist-info/RECORD
