Metadata-Version: 2.1
Name: voluxaudio
Version: 0.9.0
Summary: Audio kit for Volux
Home-page: https://gitlab.com/volux/voluxaudio
License: AGPLv3
Author: DrTexx
Author-email: denver.opensource@tutanota.com
Requires-Python: >=3.8.1,<4.0.0
Classifier: License :: Other/Proprietary License
Classifier: Programming Language :: Python :: 3
Classifier: Programming Language :: Python :: 3.9
Classifier: Programming Language :: Python :: 3.10
Classifier: Programming Language :: Python :: 3.11
Requires-Dist: numpy (>=1.23,<2.0)
Requires-Dist: numpy-ringbuffer (>=0.2.2,<0.3.0)
Requires-Dist: sounddevice (>=0.4.6,<0.5.0)
Requires-Dist: volux (>=0.10.0,<0.11.0)
Project-URL: Repository, https://gitlab.com/volux/voluxaudio
